azup/__init__.py
azup/annotations.py
azup/cmd.py
azup/context.py
azup/main.py
azup/yaml.py
azup-2021.9.dist-info/METADATA
azup-2021.9.dist-info/WHEEL
azup-2021.9.dist-info/entry_points.txt
azup-2021.9.dist-info/top_level.txt
azup-2021.9.dist-info/RECORD
